{
  "rows": [
    "1+ Lip Sync Win",
    "2+ Lip Sync Wins",
    "3+ Lip Sync Wins"
  ],
  "cols": [
    "Season 15",
    "Season 14",
    "3+ Lip Sync Wins"
  ],
  "row_sql": [
    "queen_id IN (SELECT queen_id FROM queens GROUP BY queen_id HAVING SUM(lip_sync_wins) >= 1)",
    "queen_id IN (SELECT queen_id FROM queens GROUP BY queen_id HAVING SUM(lip_sync_wins) >= 2)",
    "queen_id IN (SELECT queen_id FROM queens GROUP BY queen_id HAVING SUM(lip_sync_wins) >= 3)"
  ],
  "col_sql": [
    "queen_id IN (SELECT queen_id FROM queens WHERE season_no = 15)",
    "queen_id IN (SELECT queen_id FROM queens WHERE season_no = 14)",
    "queen_id IN (SELECT queen_id FROM queens GROUP BY queen_id HAVING SUM(lip_sync_wins) >= 3)"
  ],
  "row_desc": [
    "Queen has at least one lip sync win.",
    "Queen has at least two lip sync wins.",
    "Queen has at least three lip sync wins."
  ],
  "col_desc": [
    "Queen appeared in Season 15 (any franchise).",
    "Queen appeared in Season 14 (any franchise).",
    "Queen has at least three lip sync wins."
  ],
  "answers": [
    [
      "195",
      "179",
      "112"
    ],
    [
      "192",
      "178",
      "151"
    ],
    [
      "191",
      "173",
      "87"
    ]
  ]
}